photonai_neuro/__init__.py
photonai_neuro/atlas_library.py
photonai_neuro/atlas_mapper.py
photonai_neuro/brain_atlas.py
photonai_neuro/brain_mask.py
photonai_neuro/neuro_branch.py
photonai_neuro/nifti_transformations.py
photonai_neuro/objects.py
photonai_neuro/photonai_neuro.json
photonai_neuro/util.py
photonai_neuro/version.py
photonai_neuro/atlases/AAL_SPM12/AAL.nii.gz
photonai_neuro/atlases/AAL_SPM12/AAL_labels.txt
photonai_neuro/atlases/Cerebellum/P_08_Cere.nii.gz
photonai_neuro/atlases/Cerebellum/VBM_Cerebellum_from_AAL.nii.gz
photonai_neuro/atlases/HarvardOxford/HarvardOxford-cort-maxprob-thr25.nii.gz
photonai_neuro/atlases/HarvardOxford/HarvardOxford-cort-maxprob-thr25_labels.txt
photonai_neuro/atlases/HarvardOxford/HarvardOxford-cort-maxprob-thr50.nii.gz
photonai_neuro/atlases/HarvardOxford/HarvardOxford-cort-maxprob-thr50_labels.txt
photonai_neuro/atlases/HarvardOxford/HarvardOxford-sub-maxprob-thr25.nii.gz
photonai_neuro/atlases/HarvardOxford/HarvardOxford-sub-maxprob-thr25_labels.txt
photonai_neuro/atlases/HarvardOxford/HarvardOxford-sub-maxprob-thr50.nii.gz
photonai_neuro/atlases/HarvardOxford/HarvardOxford-sub-maxprob-thr50_labels.txt
photonai_neuro/atlases/ICBM152/mni_icbm152_gm_tal_nlin_sym_09a.nii.gz
photonai_neuro/atlases/ICBM152/mni_icbm152_t1_tal_nlin_sym_09a_mask.nii.gz
photonai_neuro/atlases/ICBM152/mni_icbm152_wm_tal_nlin_sym_09a.nii.gz
photonai_neuro/atlases/Schaefer/Schaefer2018_1000Parcels_17Networks_order_FSLMNI152_1mm.nii.gz
photonai_neuro/atlases/Schaefer/Schaefer2018_1000Parcels_17Networks_order_FSLMNI152_1mm_labels.txt
photonai_neuro/atlases/Schaefer/Schaefer2018_1000Parcels_7Networks_order_FSLMNI152_1mm.nii.gz
photonai_neuro/atlases/Schaefer/Schaefer2018_1000Parcels_7Networks_order_FSLMNI152_1mm_labels.txt
photonai_neuro/atlases/Schaefer/Schaefer2018_100Parcels_17Networks_order_FSLMNI152_1mm.nii.gz
photonai_neuro/atlases/Schaefer/Schaefer2018_100Parcels_17Networks_order_FSLMNI152_1mm_labels.txt
photonai_neuro-0.2.0.dist-info/AUTHORS
photonai_neuro-0.2.0.dist-info/LICENSE
photonai_neuro-0.2.0.dist-info/METADATA
photonai_neuro-0.2.0.dist-info/WHEEL
photonai_neuro-0.2.0.dist-info/pbr.json
photonai_neuro-0.2.0.dist-info/top_level.txt
photonai_neuro-0.2.0.dist-info/RECORD
