Metadata-Version: 2.1
Name: photonai-neuro
Version: 0.2.0
Summary: UNKNOWN
Home-page: https://www.photon-ai.com/
Author: PHOTONAI Team
Author-email: hahnt@uni-muenster.de
License: GPLv3
Download-URL: https://pypi.org/project/photonai_neuro/#files
Project-URL: Source Code, https://github.com/wwu-mmll/photonai_neuro
Project-URL: Bug Tracker, https://github.com/wwu-mmll/photonai_neuro/issues
Keywords: machine learning,neuroimaging,MRI
Platform: UNKNOWN
Classifier: License :: OSI Approved :: GNU General Public License v3 (GPLv3)
Classifier: Topic :: Software Development :: Libraries :: Python Modules
Classifier: Topic :: Scientific/Engineering :: Artificial Intelligence
Classifier: Intended Audience :: Science/Research
License-File: LICENSE
License-File: AUTHORS
Requires-Dist: joblib
Requires-Dist: matplotlib
Requires-Dist: nibabel
Requires-Dist: nilearn
Requires-Dist: numpy
Requires-Dist: pandas
Requires-Dist: photonai
Requires-Dist: scikit-learn
Requires-Dist: scikit-image
Requires-Dist: pbr
